upload_field/__init__.py
upload_field/frontend/build/asset-manifest.json
upload_field/frontend/build/bootstrap.min.css
upload_field/frontend/build/index.html
upload_field/frontend/build/precache-manifest.30998980127c7a8d4efe0e14abdf89ea.js
upload_field/frontend/build/precache-manifest.b1b5159426d40a194d5cdc03b96b64db.js
upload_field/frontend/build/service-worker.js
upload_field/frontend/build/static/js/2.f45c76a0.chunk.js
upload_field/frontend/build/static/js/2.f45c76a0.chunk.js.LICENSE.txt
upload_field/frontend/build/static/js/2.f45c76a0.chunk.js.map
upload_field/frontend/build/static/js/main.03282d56.chunk.js
upload_field/frontend/build/static/js/main.03282d56.chunk.js.LICENSE.txt
upload_field/frontend/build/static/js/main.03282d56.chunk.js.map
upload_field/frontend/build/static/js/main.54b2e0b2.chunk.js
upload_field/frontend/build/static/js/main.54b2e0b2.chunk.js.LICENSE.txt
upload_field/frontend/build/static/js/main.54b2e0b2.chunk.js.map
upload_field/frontend/build/static/js/runtime-main.3447dced.js
upload_field/frontend/build/static/js/runtime-main.3447dced.js.map
upload_field-0.0.4.dist-info/LICENSE
upload_field-0.0.4.dist-info/METADATA
upload_field-0.0.4.dist-info/WHEEL
upload_field-0.0.4.dist-info/top_level.txt
upload_field-0.0.4.dist-info/RECORD
